pydust_utils/__init__.py
pydust_utils/airfoil.py
pydust_utils/build_mesh.py
pydust_utils/c81generator.py
pydust_utils/launcher.py
pydust_utils/mesh.py
pydust_utils/parse_postpro_files.py
pydust_utils/postpro.py
pydust_utils/py.typed
pydust_utils/visualization.py
pydust_utils/write_reference.py
pydust_utils-0.1.8.dist-info/METADATA
pydust_utils-0.1.8.dist-info/WHEEL
pydust_utils-0.1.8.dist-info/top_level.txt
pydust_utils-0.1.8.dist-info/RECORD
