Metadata-Version: 2.4
Name: pydust_utils
Version: 0.1.8
Summary: Python utilities for DUST pre- and postprocessing
Author-email: Alessandro Cocco <alessandro.cocco@polimi.it>
License: MIT
Project-URL: Homepage, https://www.dust.polimi.it/
Project-URL: Repository, https://public.gitlab.polimi.it/DAER/dust
Project-URL: Issues, https://public.gitlab.polimi.it/DAER/dust/-/issues
Keywords: aerodynamics,cfd,dust,mesh-generation,post-processing
Classifier: Development Status :: 2 - Pre-Alpha
Classifier: Intended Audience :: Science/Research
Classifier: License :: OSI Approved :: MIT License
Classifier: Programming Language :: Python :: 3
Classifier: Programming Language :: Python :: 3.9
Classifier: Programming Language :: Python :: 3.10
Classifier: Programming Language :: Python :: 3.11
Classifier: Programming Language :: Python :: 3.12
Classifier: Topic :: Scientific/Engineering
Requires-Python: >=3.9
Requires-Dist: numpy>=1.20.0
Requires-Dist: pandas>=2.0.0
Requires-Dist: AeroSandbox>=4.2.0
Requires-Dist: pyvista>=0.43.0
Requires-Dist: pyvistaqt>=0.11.0
Requires-Dist: matplotlib>=3.5.0
Requires-Dist: seaborn>=0.12.0
Requires-Dist: jupyter>=1.0.0
Requires-Dist: ipywidgets>=8.0.0
Requires-Dist: ipympl>=0.9.0
Requires-Dist: h5py>=3.0.0
Provides-Extra: dev
Requires-Dist: pytest>=7.0; extra == "dev"
Requires-Dist: pytest-cov>=4.0; extra == "dev"
Requires-Dist: black>=23.0; extra == "dev"
Requires-Dist: ruff>=0.1.0; extra == "dev"
Requires-Dist: mypy>=1.0; extra == "dev"
Provides-Extra: docs
Requires-Dist: sphinx>=5.0; extra == "docs"
Requires-Dist: sphinx-book-theme>=1.0; extra == "docs"
Requires-Dist: sphinx-autodoc-typehints>=1.23; extra == "docs"
Requires-Dist: numpydoc>=1.5; extra == "docs"
